labeler/labeler.py
labeler/util.py
labeler/libs/.gitkeep
labeler/libs/libkoverse_labeler-arm64-apple-darwin.dylib
cch_labeler-0.0.0.dist-info/METADATA
cch_labeler-0.0.0.dist-info/WHEEL
cch_labeler-0.0.0.dist-info/top_level.txt
cch_labeler-0.0.0.dist-info/RECORD
