Metadata-Version: 2.1
Name: cch-labeler
Version: 0.0.0
Summary: A package for labeling data
Author-email: Chih-Chieh Huang <cchdroid@gmail.com>
Keywords: labeling
Classifier: Programming Language :: Python :: 3
Classifier: Operating System :: OS Independent
Classifier: License :: OSI Approved :: GNU General Public License v3 (GPLv3)
Requires-Python: >=3.10
Requires-Dist: cffi >=1.16.0
Provides-Extra: dev
Requires-Dist: pytest >=7.4.3 ; extra == 'dev'
